ortools_vrp_wrapper/problem.py
ortools_vrp_wrapper/routing_model.py
ortools_vrp_wrapper/solution.py
ortools_vrp_wrapper-0.0.4.dist-info/LICENSE
ortools_vrp_wrapper-0.0.4.dist-info/METADATA
ortools_vrp_wrapper-0.0.4.dist-info/WHEEL
ortools_vrp_wrapper-0.0.4.dist-info/top_level.txt
ortools_vrp_wrapper-0.0.4.dist-info/RECORD
