Metadata-Version: 2.1
Name: ortools-vrp-wrapper
Version: 0.0.4
Author-email: Marcos Nogueira <marcos.nogueira1@gmail.com>
License: Copyright (c) 2022 Marcos Silva Nogueira
License-File: LICENSE
Requires-Dist: dataclasses-json
Requires-Dist: ortools
